[
  {
    "brand": "Maruti Suzuki",
    "model": "Alto K10",
    "variant": "VXI",
    "price": 450000,
    "mileage": 24.9,
    "fuelType": "petrol",
    "transmission": "manual",
    "bodyType": "hatchback",
    "safetyRating": 2,
    "performanceScore": 4,
    "comfortScore": 5,
    "seatingCapacity": 5,
    "imageUrl": "https://images.unsplash.com/photo-1549317661-bd32c8ce0db2?w=800&q=80",
    "pros": ["Excellent mileage", "Low maintenance cost", "Easy city parking", "Wide service network"],
    "cons": ["Basic safety features", "Limited boot space", "Highway stability average"]
  },
  {
    "brand": "Maruti Suzuki",
    "model": "Swift",
    "variant": "ZXI",
    "price": 780000,
    "mileage": 23.2,
    "fuelType": "petrol",
    "transmission": "manual",
    "bodyType": "hatchback",
    "safetyRating": 3,
    "performanceScore": 6,
    "comfortScore": 6,
    "seatingCapacity": 5,
    "imageUrl": "https://images.unsplash.com/photo-1552519507-da3b142c6e3d?w=800&q=80",
    "pros": ["Sporty handling", "Good resale value", "Reliable engine", "Feature-rich variants"],
    "cons": ["Rear seat space tight", "Boot space limited", "Road noise at highway speeds"]
  },
  {
    "brand": "Maruti Suzuki",
    "model": "Baleno",
    "variant": "Alpha",
    "price": 920000,
    "mileage": 22.9,
    "fuelType": "petrol",
    "transmission": "automatic",
    "bodyType": "hatchback",
    "safetyRating": 3,
    "performanceScore": 6,
    "comfortScore": 7,
    "seatingCapacity": 5,
    "imageUrl": "https://images.unsplash.com/photo-1494976388531-d1058494cdd8?w=800&q=80",
    "pros": ["Spacious cabin", "Smooth AMT", "Premium feel", "Strong mileage"],
    "cons": ["AMT can feel jerky", "Build quality average", "Higher price than rivals"]
  },
  {
    "brand": "Maruti Suzuki",
    "model": "Brezza",
    "variant": "ZXI+",
    "price": 1150000,
    "mileage": 19.8,
    "fuelType": "petrol",
    "transmission": "automatic",
    "bodyType": "suv",
    "safetyRating": 4,
    "performanceScore": 6,
    "comfortScore": 7,
    "seatingCapacity": 5,
    "imageUrl": "https://images.unsplash.com/photo-1519641471654-76ce01057ad1?w=800&q=80",
    "pros": ["Compact SUV practicality", "Good ground clearance", "Reliable powertrain", "Strong brand trust"],
    "cons": ["Rear seat could be wider", "Boot space moderate", "No diesel option"]
  },
  {
    "brand": "Maruti Suzuki",
    "model": "Ertiga",
    "variant": "ZXI+",
    "price": 1180000,
    "mileage": 20.5,
    "fuelType": "petrol",
    "transmission": "manual",
    "bodyType": "muv",
    "safetyRating": 3,
    "performanceScore": 5,
    "comfortScore": 7,
    "seatingCapacity": 7,
    "imageUrl": "https://images.unsplash.com/photo-1544636331-e26879cd4d9b?w=800&q=80",
    "pros": ["7-seater flexibility", "Comfortable ride", "Low running costs", "Good for families"],
    "cons": ["Third row tight for adults", "Highway performance average", "Plastic-heavy interior"]
  },
  {
    "brand": "Maruti Suzuki",
    "model": "Grand Vitara",
    "variant": "Alpha+",
    "price": 1950000,
    "mileage": 27.9,
    "fuelType": "hybrid",
    "transmission": "automatic",
    "bodyType": "suv",
    "safetyRating": 4,
    "performanceScore": 7,
    "comfortScore": 8,
    "seatingCapacity": 5,
    "imageUrl": "https://images.unsplash.com/photo-1533473359931-30a550bce877?w=800&q=80",
    "pros": ["Excellent hybrid mileage", "Panoramic sunroof", "Premium features", "All-wheel drive option"],
    "cons": ["Premium pricing", "Rear visibility limited", "Waiting periods common"]
  },
  {
    "brand": "Maruti Suzuki",
    "model": "Fronx",
    "variant": "Alpha Turbo",
    "price": 1250000,
    "mileage": 20.5,
    "fuelType": "petrol",
    "transmission": "automatic",
    "bodyType": "suv",
    "safetyRating": 3,
    "performanceScore": 7,
    "comfortScore": 7,
    "seatingCapacity": 5,
    "imageUrl": "https://images.unsplash.com/photo-1503376780353-7e6692767b70?w=800&q=80",
    "pros": ["Turbo performance", "Stylish coupe-SUV design", "Feature loaded", "Good city mileage"],
    "cons": ["Rear headroom reduced", "Boot space smaller", "Turbo lag noticeable"]
  },
  {
    "brand": "Maruti Suzuki",
    "model": "Celerio",
    "variant": "VXI",
    "price": 580000,
    "mileage": 26.7,
    "fuelType": "petrol",
    "transmission": "manual",
    "bodyType": "hatchback",
    "safetyRating": 2,
    "performanceScore": 4,
    "comfortScore": 5,
    "seatingCapacity": 5,
    "imageUrl": "https://images.unsplash.com/photo-1542362567-b07e54358753?w=800&q=80",
    "pros": ["Outstanding mileage", "Affordable price", "Easy to drive", "Low maintenance"],
    "cons": ["Basic interiors", "Weak highway performance", "Minimal safety tech"]
  },
  {
    "brand": "Maruti Suzuki",
    "model": "Wagon R",
    "variant": "ZXI+",
    "price": 720000,
    "mileage": 25.2,
    "fuelType": "cng",
    "transmission": "manual",
    "bodyType": "hatchback",
    "safetyRating": 2,
    "performanceScore": 4,
    "comfortScore": 6,
    "seatingCapacity": 5,
    "imageUrl": "https://images.unsplash.com/photo-1583121274602-3e2820c698ab?w=800&q=80",
    "pros": ["Tall boy design", "Excellent CNG mileage", "Spacious headroom", "Low running cost"],
    "cons": ["Boxy looks", "Highway stability average", "CNG boot space reduced"]
  },
  {
    "brand": "Maruti Suzuki",
    "model": "Dzire",
    "variant": "ZXI+",
    "price": 980000,
    "mileage": 24.1,
    "fuelType": "petrol",
    "transmission": "automatic",
    "bodyType": "sedan",
    "safetyRating": 3,
    "performanceScore": 5,
    "comfortScore": 7,
    "seatingCapacity": 5,
    "imageUrl": "https://images.unsplash.com/photo-1618843479313-40f8afb4b4d8?w=800&q=80",
    "pros": ["Comfortable sedan ride", "Good mileage", "Decent boot space", "Reliable for taxi use"],
    "cons": ["Rear seat headroom limited", "Design dated", "Road noise on highways"]
  },
  {
    "brand": "Hyundai",
    "model": "i20",
    "variant": "Asta",
    "price": 1050000,
    "mileage": 20.3,
    "fuelType": "petrol",
    "transmission": "automatic",
    "bodyType": "hatchback",
    "safetyRating": 3,
    "performanceScore": 7,
    "comfortScore": 8,
    "seatingCapacity": 5,
    "imageUrl": "https://images.unsplash.com/photo-1555215695-3004980ad54e?w=800&q=80",
    "pros": ["Premium interiors", "Feature-rich", "Smooth DCT option", "Strong build quality"],
    "cons": ["Rear visibility limited", "DCT can heat in traffic", "Higher maintenance than Maruti"]
  },
  {
    "brand": "Hyundai",
    "model": "Venue",
    "variant": "SX Turbo",
    "price": 1350000,
    "mileage": 18.2,
    "fuelType": "petrol",
    "transmission": "automatic",
    "bodyType": "suv",
    "safetyRating": 4,
    "performanceScore": 7,
    "comfortScore": 7,
    "seatingCapacity": 5,
    "imageUrl": "https://images.unsplash.com/photo-1511919884226-fd3cad34687c?w=800&q=80",
    "pros": ["Connected car features", "Turbo engine punch", "Compact footprint", "Multiple transmission options"],
    "cons": ["Rear seat space tight", "Boot space average", "Turbo variants pricey"]
  },
  {
    "brand": "Hyundai",
    "model": "Creta",
    "variant": "SX(O)",
    "price": 1850000,
    "mileage": 17.4,
    "fuelType": "diesel",
    "transmission": "automatic",
    "bodyType": "suv",
    "safetyRating": 5,
    "performanceScore": 8,
    "comfortScore": 8,
    "seatingCapacity": 5,
    "imageUrl": "https://images.unsplash.com/photo-1606664515524-ed2f786a0bd6?w=800&q=80",
    "pros": ["Segment-leading features", "Refined diesel AT", "Strong safety", "Premium cabin"],
    "cons": ["Price on higher side", "Diesel maintenance cost", "Waiting periods"]
  },
  {
    "brand": "Hyundai",
    "model": "Verna",
    "variant": "SX(O) Turbo",
    "price": 1750000,
    "mileage": 18.6,
    "fuelType": "petrol",
    "transmission": "automatic",
    "bodyType": "sedan",
    "safetyRating": 5,
    "performanceScore": 8,
    "comfortScore": 8,
    "seatingCapacity": 5,
    "imageUrl": "https://images.unsplash.com/photo-1617531653332-bd46c24f2068?w=800&q=80",
    "pros": ["Powerful turbo engine", "Premium sedan feel", "ADAS features", "Comfortable rear seat"],
    "cons": ["Expensive top variants", "Low ground clearance", "Turbo mileage drops in city"]
  },
  {
    "brand": "Hyundai",
    "model": "Exter",
    "variant": "SX",
    "price": 980000,
    "mileage": 19.4,
    "fuelType": "petrol",
    "transmission": "manual",
    "bodyType": "suv",
    "safetyRating": 3,
    "performanceScore": 5,
    "comfortScore": 6,
    "seatingCapacity": 5,
    "imageUrl": "https://images.unsplash.com/photo-1492144534655-ae79c964c9d7?w=800&q=80",
    "pros": ["Affordable micro-SUV", "Good features for price", "Easy city driving", "Distinctive styling"],
    "cons": ["Three-cylinder engine refinement", "Limited rear space", "Highway performance modest"]
  },
  {
    "brand": "Hyundai",
    "model": "Alcazar",
    "variant": "Signature",
    "price": 2100000,
    "mileage": 16.2,
    "fuelType": "diesel",
    "transmission": "automatic",
    "bodyType": "suv",
    "safetyRating": 5,
    "performanceScore": 7,
    "comfortScore": 9,
    "seatingCapacity": 7,
    "imageUrl": "https://images.unsplash.com/photo-1533473359931-30a550bce877?w=800&q=80",
    "pros": ["6/7 seat luxury", "Captain seats option", "Premium features", "Comfortable ride"],
    "cons": ["Heavy in city traffic", "Third row best for kids", "High price point"]
  },
  {
    "brand": "Hyundai",
    "model": "Aura",
    "variant": "SX+",
    "price": 920000,
    "mileage": 22.7,
    "fuelType": "cng",
    "transmission": "manual",
    "bodyType": "sedan",
    "safetyRating": 3,
    "performanceScore": 5,
    "comfortScore": 6,
    "seatingCapacity": 5,
    "imageUrl": "https://images.unsplash.com/photo-1619767886554-ef1f988b9453?w=800&q=80",
    "pros": ["Factory-fitted CNG", "Sedan comfort", "Good mileage", "Affordable sedan"],
    "cons": ["Design plain", "Performance average", "Limited boot with CNG"]
  },
  {
    "brand": "Hyundai",
    "model": "Ioniq 5",
    "variant": "Long Range",
    "price": 4650000,
    "mileage": 631,
    "fuelType": "electric",
    "transmission": "automatic",
    "bodyType": "suv",
    "safetyRating": 5,
    "performanceScore": 9,
    "comfortScore": 9,
    "seatingCapacity": 5,
    "imageUrl": "https://images.unsplash.com/photo-1593941707882-a5bba14938bc?w=800&q=80",
    "pros": ["Ultra-fast charging", "Premium EV design", "Spacious cabin", "Strong performance"],
    "cons": ["Very expensive", "Limited charging infra", "Large size for city"]
  },
  {
    "brand": "Tata",
    "model": "Punch",
    "variant": "Accomplished",
    "price": 950000,
    "mileage": 20.1,
    "fuelType": "petrol",
    "transmission": "manual",
    "bodyType": "suv",
    "safetyRating": 5,
    "performanceScore": 5,
    "comfortScore": 6,
    "seatingCapacity": 5,
    "imageUrl": "https://images.unsplash.com/photo-1549317661-bd32c8ce0db2?w=800&q=80",
    "pros": ["5-star safety rating", "Compact SUV", "Good ground clearance", "Value for money"],
    "cons": ["Engine feels underpowered", "Rear seat space tight", "Infotainment lag"]
  },
  {
    "brand": "Tata",
    "model": "Nexon",
    "variant": "Fearless+",
    "price": 1450000,
    "mileage": 17.4,
    "fuelType": "diesel",
    "transmission": "manual",
    "bodyType": "suv",
    "safetyRating": 5,
    "performanceScore": 7,
    "comfortScore": 7,
    "seatingCapacity": 5,
    "imageUrl": "https://images.unsplash.com/photo-1519641471654-76ce01057ad1?w=800&q=80",
    "pros": ["5-star Global NCAP", "Strong diesel engine", "Feature-rich", "Good ride quality"],
    "cons": ["Diesel NVH", "Rear visibility limited", "Service network expanding"]
  },
  {
    "brand": "Tata",
    "model": "Nexon EV",
    "variant": "Empowered+",
    "price": 1650000,
    "mileage": 465,
    "fuelType": "electric",
    "transmission": "automatic",
    "bodyType": "suv",
    "safetyRating": 5,
    "performanceScore": 8,
    "comfortScore": 7,
    "seatingCapacity": 5,
    "imageUrl": "https://images.unsplash.com/photo-1593941707882-a5bba14938bc?w=800&q=80",
    "pros": ["Best-selling EV in India", "Good range", "Fast charging support", "Safe and practical"],
    "cons": ["Real-world range varies", "Charging time at home", "Premium over petrol Nexon"]
  },
  {
    "brand": "Tata",
    "model": "Harrier",
    "variant": "XZA+",
    "price": 2350000,
    "mileage": 16.0,
    "fuelType": "diesel",
    "transmission": "automatic",
    "bodyType": "suv",
    "safetyRating": 5,
    "performanceScore": 8,
    "comfortScore": 8,
    "seatingCapacity": 5,
    "imageUrl": "https://images.unsplash.com/photo-1533473359931-30a550bce877?w=800&q=80",
    "pros": ["Land Rover derived platform", "Premium road presence", "Strong diesel", "Excellent safety"],
    "cons": ["No petrol option", "Heavy steering in city", "Rear seat under thigh support"]
  },
  {
    "brand": "Tata",
    "model": "Safari",
    "variant": "XZA+",
    "price": 2550000,
    "mileage": 16.5,
    "fuelType": "diesel",
    "transmission": "automatic",
    "bodyType": "suv",
    "safetyRating": 5,
    "performanceScore": 8,
    "comfortScore": 9,
    "seatingCapacity": 7,
    "imageUrl": "https://images.unsplash.com/photo-1544636331-e26879cd4d9b?w=800&q=80",
    "pros": ["7-seater adventure SUV", "Premium interiors", "Strong highway cruiser", "Panoramic sunroof"],
    "cons": ["Large for city parking", "Third row for short trips", "Diesel only"]
  },
  {
    "brand": "Tata",
    "model": "Altroz",
    "variant": "Racer R3",
    "price": 1150000,
    "mileage": 19.1,
    "fuelType": "petrol",
    "transmission": "manual",
    "bodyType": "hatchback",
    "safetyRating": 5,
    "performanceScore": 7,
    "comfortScore": 7,
    "seatingCapacity": 5,
    "imageUrl": "https://images.unsplash.com/photo-1552519507-da3b142c6e3d?w=800&q=80",
    "pros": ["5-star safety hatchback", "Premium design", "Good handling", "Dual-tone options"],
    "cons": ["Rear visibility poor", "DCT discontinued", "Boot access awkward"]
  },
  {
    "brand": "Tata",
    "model": "Tiago",
    "variant": "XZ+",
    "price": 780000,
    "mileage": 23.5,
    "fuelType": "petrol",
    "transmission": "manual",
    "bodyType": "hatchback",
    "safetyRating": 4,
    "performanceScore": 5,
    "comfortScore": 6,
    "seatingCapacity": 5,
    "imageUrl": "https://images.unsplash.com/photo-1542362567-b07e54358753?w=800&q=80",
    "pros": ["Affordable and safe", "Good city car", "Decent features", "CNG option available"],
    "cons": ["Engine noise at high RPM", "Highway stability average", "Interior plastics"]
  },
  {
    "brand": "Tata",
    "model": "Tigor",
    "variant": "XZ+",
    "price": 820000,
    "mileage": 26.5,
    "fuelType": "cng",
    "transmission": "manual",
    "bodyType": "sedan",
    "safetyRating": 4,
    "performanceScore": 5,
    "comfortScore": 6,
    "seatingCapacity": 5,
    "imageUrl": "https://images.unsplash.com/photo-1618843479313-40f8afb4b4d8?w=800&q=80",
    "pros": ["CNG sedan with good mileage", "4-star safety", "Compact sedan", "Low running cost"],
    "cons": ["Fastback limits rear headroom", "Boot space reduced with CNG", "Refinement average"]
  },
  {
    "brand": "Mahindra",
    "model": "XUV700",
    "variant": "AX7",
    "price": 2650000,
    "mileage": 17.0,
    "fuelType": "diesel",
    "transmission": "automatic",
    "bodyType": "suv",
    "safetyRating": 5,
    "performanceScore": 9,
    "comfortScore": 9,
    "seatingCapacity": 7,
    "imageUrl": "https://images.unsplash.com/photo-1606664515524-ed2f786a0bd6?w=800&q=80",
    "pros": ["ADAS in segment", "Powerful engines", "Premium tech", "Spacious 7-seater"],
    "cons": ["Quality inconsistencies reported", "Large for tight cities", "Service experience varies"]
  },
  {
    "brand": "Mahindra",
    "model": "Scorpio N",
    "variant": "Z8",
    "price": 2200000,
    "mileage": 15.4,
    "fuelType": "diesel",
    "transmission": "automatic",
    "bodyType": "suv",
    "safetyRating": 5,
    "performanceScore": 8,
    "comfortScore": 7,
    "seatingCapacity": 7,
    "imageUrl": "https://images.unsplash.com/photo-1519641471654-76ce01057ad1?w=800&q=80",
    "pros": ["Iconic rugged SUV", "Strong road presence", "7-seat option", "Off-road capable"],
    "cons": ["Ride firm on bad roads", "Third row cramped", "Fuel economy modest"]
  },
  {
    "brand": "Mahindra",
    "model": "Thar",
    "variant": "LX Hard Top",
    "price": 1750000,
    "mileage": 15.2,
    "fuelType": "diesel",
    "transmission": "manual",
    "bodyType": "suv",
    "safetyRating": 4,
    "performanceScore": 7,
    "comfortScore": 5,
    "seatingCapacity": 4,
    "imageUrl": "https://images.unsplash.com/photo-1533473359931-30a550bce877?w=800&q=80",
    "pros": ["Legendary off-roader", "Convertible options", "Strong resale", "Unique personality"],
    "cons": ["Not a family daily driver", "Limited rear space", "Highway noise and ride"]
  },
  {
    "brand": "Mahindra",
    "model": "XUV300",
    "variant": "W8",
    "price": 1150000,
    "mileage": 17.0,
    "fuelType": "diesel",
    "transmission": "manual",
    "bodyType": "suv",
    "safetyRating": 5,
    "performanceScore": 7,
    "comfortScore": 7,
    "seatingCapacity": 5,
    "imageUrl": "https://images.unsplash.com/photo-1492144534655-ae79c964c9d7?w=800&q=80",
    "pros": ["Best-in-class safety", "Punchy turbo engines", "Sunroof standard", "Strong build"],
    "cons": ["Boot space very small", "Rear seat tight", "Design polarizing"]
  },
  {
    "brand": "Mahindra",
    "model": "Bolero Neo",
    "variant": "N10",
    "price": 1050000,
    "mileage": 17.2,
    "fuelType": "diesel",
    "transmission": "manual",
    "bodyType": "muv",
    "safetyRating": 3,
    "performanceScore": 5,
    "comfortScore": 5,
    "seatingCapacity": 7,
    "imageUrl": "https://images.unsplash.com/photo-1544636331-e26879cd4d9b?w=800&q=80",
    "pros": ["Rugged and reliable", "7-seater utility", "Low maintenance", "Good for rural roads"],
    "cons": ["Outdated interiors", "No automatic option", "Refinement lacking"]
  },
  {
    "brand": "Mahindra",
    "model": "XUV400",
    "variant": "EL Pro",
    "price": 1950000,
    "mileage": 456,
    "fuelType": "electric",
    "transmission": "automatic",
    "bodyType": "suv",
    "safetyRating": 5,
    "performanceScore": 8,
    "comfortScore": 7,
    "seatingCapacity": 5,
    "imageUrl": "https://images.unsplash.com/photo-1593941707882-a5bba14938bc?w=800&q=80",
    "pros": ["Long EV range", "Fast acceleration", "Spacious cabin", "Feature loaded"],
    "cons": ["Charging infrastructure needed", "Premium pricing", "Brand perception vs rivals"]
  },
  {
    "brand": "Kia",
    "model": "Seltos",
    "variant": "GTX+",
    "price": 1950000,
    "mileage": 16.8,
    "fuelType": "diesel",
    "transmission": "automatic",
    "bodyType": "suv",
    "safetyRating": 5,
    "performanceScore": 8,
    "comfortScore": 8,
    "seatingCapacity": 5,
    "imageUrl": "https://images.unsplash.com/photo-1606664515524-ed2f786a0bd6?w=800&q=80",
    "pros": ["Premium design", "Multiple powertrain options", "Connected features", "Comfortable ride"],
    "cons": ["DCT reliability concerns in past", "Price increases", "Rear middle seat firm"]
  },
  {
    "brand": "Kia",
    "model": "Sonet",
    "variant": "GTX+",
    "price": 1350000,
    "mileage": 18.4,
    "fuelType": "petrol",
    "transmission": "automatic",
    "bodyType": "suv",
    "safetyRating": 4,
    "performanceScore": 7,
    "comfortScore": 7,
    "seatingCapacity": 5,
    "imageUrl": "https://images.unsplash.com/photo-1511919884226-fd3cad34687c?w=800&q=80",
    "pros": ["Feature-packed compact SUV", "Turbo and NA options", "Bold styling", "Good safety kit"],
    "cons": ["Rear space limited", "Clutch-based auto jerky", "Sunroof reduces headroom"]
  },
  {
    "brand": "Kia",
    "model": "Carens",
    "variant": "Luxury Plus",
    "price": 1850000,
    "mileage": 16.5,
    "fuelType": "diesel",
    "transmission": "automatic",
    "bodyType": "muv",
    "safetyRating": 5,
    "performanceScore": 7,
    "comfortScore": 8,
    "seatingCapacity": 7,
    "imageUrl": "https://images.unsplash.com/photo-1544636331-e26879cd4d9b?w=800&q=80",
    "pros": ["Premium 6/7 seater", "Captain seats available", "Smooth diesel AT", "Feature rich"],
    "cons": ["Third row for kids only", "Large turning radius", "Diesel cost in city"]
  },
  {
    "brand": "Kia",
    "model": "EV6",
    "variant": "GT Line",
    "price": 6590000,
    "mileage": 708,
    "fuelType": "electric",
    "transmission": "automatic",
    "bodyType": "suv",
    "safetyRating": 5,
    "performanceScore": 10,
    "comfortScore": 9,
    "seatingCapacity": 5,
    "imageUrl": "https://images.unsplash.com/photo-1593941707882-a5bba14938bc?w=800&q=80",
    "pros": ["800V ultra-fast charging", "Stunning design", "Excellent performance", "Premium EV"],
    "cons": ["Very expensive", "Limited service network", "Large for Indian roads"]
  },
  {
    "brand": "Honda",
    "model": "City",
    "variant": "ZX CVT",
    "price": 1750000,
    "mileage": 17.8,
    "fuelType": "petrol",
    "transmission": "automatic",
    "bodyType": "sedan",
    "safetyRating": 4,
    "performanceScore": 7,
    "comfortScore": 8,
    "seatingCapacity": 5,
    "imageUrl": "https://images.unsplash.com/photo-1617531653332-bd46c24f2068?w=800&q=80",
    "pros": ["Refined CVT", "Spacious rear seat", "Reliable Honda engine", "Premium sedan feel"],
    "cons": ["Ground clearance low", "Price premium over rivals", "Rear headroom in new design"]
  },
  {
    "brand": "Honda",
    "model": "Amaze",
    "variant": "VX CVT",
    "price": 980000,
    "mileage": 19.5,
    "fuelType": "petrol",
    "transmission": "automatic",
    "bodyType": "sedan",
    "safetyRating": 4,
    "performanceScore": 6,
    "comfortScore": 7,
    "seatingCapacity": 5,
    "imageUrl": "https://images.unsplash.com/photo-1618843479313-40f8afb4b4d8?w=800&q=80",
    "pros": ["Compact sedan", "Smooth CVT", "Good mileage", "Easy city driving"],
    "cons": ["Interior dated", "Boot space average", "Rear seat narrow"]
  },
  {
    "brand": "Honda",
    "model": "Elevate",
    "variant": "ZX",
    "price": 1650000,
    "mileage": 16.9,
    "fuelType": "petrol",
    "transmission": "automatic",
    "bodyType": "suv",
    "safetyRating": 4,
    "performanceScore": 7,
    "comfortScore": 8,
    "seatingCapacity": 5,
    "imageUrl": "https://images.unsplash.com/photo-1519641471654-76ce01057ad1?w=800&q=80",
    "pros": ["Honda reliability", "Spacious cabin", "Good ride comfort", "Strong safety kit"],
    "cons": ["No diesel or turbo", "Mileage average", "Design conservative"]
  },
  {
    "brand": "Toyota",
    "model": "Innova Crysta",
    "variant": "ZX",
    "price": 2650000,
    "mileage": 14.1,
    "fuelType": "diesel",
    "transmission": "automatic",
    "bodyType": "muv",
    "safetyRating": 5,
    "performanceScore": 7,
    "comfortScore": 9,
    "seatingCapacity": 7,
    "imageUrl": "https://images.unsplash.com/photo-1544636331-e26879cd4d9b?w=800&q=80",
    "pros": ["Unmatched reliability", "Comfortable 7-seater", "Strong resale", "Tour-ready"],
    "cons": ["Expensive", "Diesel only", "Large for city use"]
  },
  {
    "brand": "Toyota",
    "model": "Innova Hycross",
    "variant": "ZX Hybrid",
    "price": 3050000,
    "mileage": 21.1,
    "fuelType": "hybrid",
    "transmission": "automatic",
    "bodyType": "muv",
    "safetyRating": 5,
    "performanceScore": 8,
    "comfortScore": 9,
    "seatingCapacity": 7,
    "imageUrl": "https://images.unsplash.com/photo-1544636331-e26879cd4d9b?w=800&q=80",
    "pros": ["Hybrid efficiency in MPV", "Premium captain seats", "Smooth and quiet", "Toyota reliability"],
    "cons": ["Very expensive", "Waiting periods long", "Third row access tricky"]
  },
  {
    "brand": "Toyota",
    "model": "Fortuner",
    "variant": "4x4 AT",
    "price": 5200000,
    "mileage": 12.8,
    "fuelType": "diesel",
    "transmission": "automatic",
    "bodyType": "suv",
    "safetyRating": 5,
    "performanceScore": 9,
    "comfortScore": 8,
    "seatingCapacity": 7,
    "imageUrl": "https://images.unsplash.com/photo-1533473359931-30a550bce877?w=800&q=80",
    "pros": ["Premium ladder-frame SUV", "Excellent off-road", "Strong resale", "Commanding presence"],
    "cons": ["Very expensive", "Poor city mileage", "Large and heavy"]
  },
  {
    "brand": "Toyota",
    "model": "Glanza",
    "variant": "V",
    "price": 780000,
    "mileage": 22.4,
    "fuelType": "petrol",
    "transmission": "manual",
    "bodyType": "hatchback",
    "safetyRating": 3,
    "performanceScore": 5,
    "comfortScore": 6,
    "seatingCapacity": 5,
    "imageUrl": "https://images.unsplash.com/photo-1552519507-da3b142c6e3d?w=800&q=80",
    "pros": ["Toyota badge reliability", "Good mileage", "Easy ownership", "Compact hatchback"],
    "cons": ["Rebadged product", "Limited differentiation", "Features basic"]
  },
  {
    "brand": "Toyota",
    "model": "Urban Cruiser Hyryder",
    "variant": "V Hybrid",
    "price": 1650000,
    "mileage": 27.9,
    "fuelType": "hybrid",
    "transmission": "automatic",
    "bodyType": "suv",
    "safetyRating": 4,
    "performanceScore": 7,
    "comfortScore": 8,
    "seatingCapacity": 5,
    "imageUrl": "https://images.unsplash.com/photo-1519641471654-76ce01057ad1?w=800&q=80",
    "pros": ["Strong hybrid mileage", "Toyota reliability", "Comfortable SUV", "All-wheel drive option"],
    "cons": ["Premium over rivals", "Performance modest", "Infotainment average"]
  },
  {
    "brand": "MG",
    "model": "Hector",
    "variant": "Sharp Pro",
    "price": 1950000,
    "mileage": 15.0,
    "fuelType": "petrol",
    "transmission": "automatic",
    "bodyType": "suv",
    "safetyRating": 4,
    "performanceScore": 7,
    "comfortScore": 8,
    "seatingCapacity": 5,
    "imageUrl": "https://images.unsplash.com/photo-1606664515524-ed2f786a0bd6?w=800&q=80",
    "pros": ["Large panoramic sunroof", "Connected car tech", "Spacious cabin", "Premium feel"],
    "cons": ["Petrol only no diesel", "Heavy in city", "Service network growing"]
  },
  {
    "brand": "MG",
    "model": "Astor",
    "variant": "Sharp",
    "price": 1550000,
    "mileage": 17.5,
    "fuelType": "petrol",
    "transmission": "automatic",
    "bodyType": "suv",
    "safetyRating": 4,
    "performanceScore": 7,
    "comfortScore": 7,
    "seatingCapacity": 5,
    "imageUrl": "https://images.unsplash.com/photo-1492144534655-ae79c964c9d7?w=800&q=80",
    "pros": ["ADAS in segment", "Turbo engine", "Premium features", "Distinctive styling"],
    "cons": ["Rear seat space average", "Turbo mileage drops", "Brand resale lower"]
  },
  {
    "brand": "MG",
    "model": "ZS EV",
    "variant": "Exclusive",
    "price": 2250000,
    "mileage": 461,
    "fuelType": "electric",
    "transmission": "automatic",
    "bodyType": "suv",
    "safetyRating": 5,
    "performanceScore": 8,
    "comfortScore": 7,
    "seatingCapacity": 5,
    "imageUrl": "https://images.unsplash.com/photo-1593941707882-a5bba14938bc?w=800&q=80",
    "pros": ["Good EV range", "Fast DC charging", "Feature loaded", "Comfortable ride"],
    "cons": ["Real-world range varies", "Service network limited", "Depreciation concerns"]
  },
  {
    "brand": "MG",
    "model": "Comet EV",
    "variant": "Plush",
    "price": 780000,
    "mileage": 230,
    "fuelType": "electric",
    "transmission": "automatic",
    "bodyType": "hatchback",
    "safetyRating": 3,
    "performanceScore": 4,
    "comfortScore": 5,
    "seatingCapacity": 4,
    "imageUrl": "https://images.unsplash.com/photo-1593941707882-a5bba14938bc?w=800&q=80",
    "pros": ["Affordable city EV", "Easy parking", "Low running cost", "Unique design"],
    "cons": ["Limited range", "Two-door access awkward", "Not for highway"]
  },
  {
    "brand": "Skoda",
    "model": "Kushaq",
    "variant": "Style",
    "price": 1550000,
    "mileage": 17.9,
    "fuelType": "petrol",
    "transmission": "automatic",
    "bodyType": "suv",
    "safetyRating": 5,
    "performanceScore": 7,
    "comfortScore": 8,
    "seatingCapacity": 5,
    "imageUrl": "https://images.unsplash.com/photo-1519641471654-76ce01057ad1?w=800&q=80",
    "pros": ["European build quality", "Strong TSI engines", "5-star safety", "Premium interiors"],
    "cons": ["Rear seat space tight", "Service cost higher", "Limited variants"]
  },
  {
    "brand": "Skoda",
    "model": "Slavia",
    "variant": "Style",
    "price": 1650000,
    "mileage": 19.5,
    "fuelType": "petrol",
    "transmission": "automatic",
    "bodyType": "sedan",
    "safetyRating": 5,
    "performanceScore": 8,
    "comfortScore": 8,
    "seatingCapacity": 5,
    "imageUrl": "https://images.unsplash.com/photo-1617531653332-bd46c24f2068?w=800&q=80",
    "pros": ["Powerful TSI turbo", "Premium sedan dynamics", "5-star safety", "Spacious boot"],
    "cons": ["Low ground clearance", "Rear headroom limited", "Skoda service network"]
  },
  {
    "brand": "Volkswagen",
    "model": "Virtus",
    "variant": "GT",
    "price": 1750000,
    "mileage": 18.8,
    "fuelType": "petrol",
    "transmission": "automatic",
    "bodyType": "sedan",
    "safetyRating": 5,
    "performanceScore": 9,
    "comfortScore": 8,
    "seatingCapacity": 5,
    "imageUrl": "https://images.unsplash.com/photo-1618843479313-40f8afb4b4d8?w=800&q=80",
    "pros": ["GT performance sedan", "Excellent handling", "Premium build", "Strong safety"],
    "cons": ["GT variant expensive", "Low ground clearance", "VW service costs"]
  },
  {
    "brand": "Volkswagen",
    "model": "Taigun",
    "variant": "GT Plus",
    "price": 1850000,
    "mileage": 17.2,
    "fuelType": "petrol",
    "transmission": "automatic",
    "bodyType": "suv",
    "safetyRating": 5,
    "performanceScore": 8,
    "comfortScore": 8,
    "seatingCapacity": 5,
    "imageUrl": "https://images.unsplash.com/photo-1606664515524-ed2f786a0bd6?w=800&q=80",
    "pros": ["GT performance SUV", "European dynamics", "5-star safety", "Premium cabin"],
    "cons": ["Rear space average", "Pricey top trims", "Limited dealer network"]
  },
  {
    "brand": "Renault",
    "model": "Kiger",
    "variant": "RXZ Turbo",
    "price": 1050000,
    "mileage": 19.0,
    "fuelType": "petrol",
    "transmission": "manual",
    "bodyType": "suv",
    "safetyRating": 3,
    "performanceScore": 6,
    "comfortScore": 6,
    "seatingCapacity": 5,
    "imageUrl": "https://images.unsplash.com/photo-1492144534655-ae79c964c9d7?w=800&q=80",
    "pros": ["Affordable compact SUV", "Turbo option", "Distinctive design", "Good features"],
    "cons": ["CVT not offered on turbo", "Rear space tight", "Resale value average"]
  },
  {
    "brand": "Renault",
    "model": "Triber",
    "variant": "RXZ",
    "price": 820000,
    "mileage": 19.0,
    "fuelType": "petrol",
    "transmission": "manual",
    "bodyType": "muv",
    "safetyRating": 3,
    "performanceScore": 4,
    "comfortScore": 6,
    "seatingCapacity": 7,
    "imageUrl": "https://images.unsplash.com/photo-1544636331-e26879cd4d9b?w=800&q=80",
    "pros": ["Modular 7-seater", "Very affordable", "Easy third row access", "Good for large families"],
    "cons": ["Engine underpowered", "Highway performance weak", "Basic safety kit"]
  },
  {
    "brand": "Nissan",
    "model": "Magnite",
    "variant": "Turbo CVT",
    "price": 1150000,
    "mileage": 18.0,
    "fuelType": "petrol",
    "transmission": "automatic",
    "bodyType": "suv",
    "safetyRating": 4,
    "performanceScore": 6,
    "comfortScore": 6,
    "seatingCapacity": 5,
    "imageUrl": "https://images.unsplash.com/photo-1511919884226-fd3cad34687c?w=800&q=80",
    "pros": ["Affordable turbo SUV", "Bold design", "Good feature list", "Compact footprint"],
    "cons": ["CVT refinement average", "Rear seat narrow", "Brand resale weak"]
  },
  {
    "brand": "Citroen",
    "model": "C3",
    "variant": "Shine",
    "price": 850000,
    "mileage": 19.8,
    "fuelType": "petrol",
    "transmission": "manual",
    "bodyType": "hatchback",
    "safetyRating": 3,
    "performanceScore": 5,
    "comfortScore": 7,
    "seatingCapacity": 5,
    "imageUrl": "https://images.unsplash.com/photo-1552519507-da3b142c6e3d?w=800&q=80",
    "pros": ["Comfort-focused suspension", "Unique design", "Affordable", "Smooth ride"],
    "cons": ["Service network limited", "Features basic", "Resale uncertain"]
  },
  {
    "brand": "Citroen",
    "model": "C3 Aircross",
    "variant": "Max",
    "price": 1350000,
    "mileage": 18.5,
    "fuelType": "petrol",
    "transmission": "manual",
    "bodyType": "suv",
    "safetyRating": 4,
    "performanceScore": 6,
    "comfortScore": 8,
    "seatingCapacity": 7,
    "imageUrl": "https://images.unsplash.com/photo-1544636331-e26879cd4d9b?w=800&q=80",
    "pros": ["7-seater on budget", "Comfortable ride", "Distinctive styling", "Good ground clearance"],
    "cons": ["Third row very tight", "Single engine option", "Limited dealers"]
  },
  {
    "brand": "Jeep",
    "model": "Compass",
    "variant": "Model S",
    "price": 2950000,
    "mileage": 14.5,
    "fuelType": "diesel",
    "transmission": "automatic",
    "bodyType": "suv",
    "safetyRating": 5,
    "performanceScore": 8,
    "comfortScore": 8,
    "seatingCapacity": 5,
    "imageUrl": "https://images.unsplash.com/photo-1533473359931-30a550bce877?w=800&q=80",
    "pros": ["Premium Jeep character", "Strong diesel", "Excellent safety", "Off-road capable"],
    "cons": ["Expensive", "Rear space average", "Maintenance costly"]
  },
  {
    "brand": "BMW",
    "model": "2 Series Gran Coupe",
    "variant": "M Sport",
    "price": 4500000,
    "mileage": 14.8,
    "fuelType": "petrol",
    "transmission": "automatic",
    "bodyType": "coupe",
    "safetyRating": 5,
    "performanceScore": 9,
    "comfortScore": 8,
    "seatingCapacity": 5,
    "imageUrl": "https://images.unsplash.com/photo-1555215695-3004980ad54e?w=800&q=80",
    "pros": ["Premium BMW dynamics", "Strong performance", "Luxury features", "Status appeal"],
    "cons": ["Very expensive", "Low ground clearance", "High maintenance"]
  },
  {
    "brand": "Mercedes-Benz",
    "model": "A-Class Limousine",
    "variant": "200",
    "price": 4200000,
    "mileage": 15.5,
    "fuelType": "petrol",
    "transmission": "automatic",
    "bodyType": "sedan",
    "safetyRating": 5,
    "performanceScore": 8,
    "comfortScore": 9,
    "seatingCapacity": 5,
    "imageUrl": "https://images.unsplash.com/photo-1618843479313-40f8afb4b4d8?w=800&q=80",
    "pros": ["Entry luxury Mercedes", "Premium interiors", "Smooth ride", "Brand prestige"],
    "cons": ["Expensive ownership", "Rear space tight", "Low ground clearance"]
  },
  {
    "brand": "Maruti Suzuki",
    "model": "Invicto",
    "variant": "Alpha+",
    "price": 2850000,
    "mileage": 20.7,
    "fuelType": "hybrid",
    "transmission": "automatic",
    "bodyType": "muv",
    "safetyRating": 5,
    "performanceScore": 7,
    "comfortScore": 9,
    "seatingCapacity": 7,
    "imageUrl": "https://images.unsplash.com/photo-1544636331-e26879cd4d9b?w=800&q=80",
    "pros": ["Hybrid MPV efficiency", "Captain seats luxury", "Toyota reliability", "Premium features"],
    "cons": ["Very expensive", "Large footprint", "Waiting periods"]
  }
]
